CHANGES.txt
LICENSE.txt
MANIFEST.in
README.md
README.rst
setup.cfg
setup.py
ndb_orm/__init__.py
ndb_orm/datastore_errors.py
ndb_orm/datastore_types.py
ndb_orm/entity.py
ndb_orm/helpers.py
ndb_orm/key.py
ndb_orm/model.py
ndb_orm/msgprop.py
ndb_orm/utils.py
ndb_orm.egg-info/PKG-INFO
ndb_orm.egg-info/SOURCES.txt
ndb_orm.egg-info/dependency_links.txt
ndb_orm.egg-info/not-zip-safe
ndb_orm.egg-info/requires.txt
ndb_orm.egg-info/top_level.txt