Metadata-Version: 1.1
Name: ndb-orm
Version: 0.8.0
Summary: google datatstore ndb orm which might be used with google-cloud-datastore (python3 compatible)
Home-page: https://github.com/berlincode/ndb-orm
Author: Ulf Bartel
Author-email: elastic.code@gmail.com
License: Apache 2.0
Keywords: ndb,model,orm,app engine standard,flexible,datastore,python3,migrate
Platform: UNKNOWN
Classifier: Intended Audience :: Developers
Classifier: License :: OSI Approved :: Apache Software License
Classifier: Natural Language :: English
Classifier: Programming Language :: Python :: 2.7
Classifier: Programming Language :: Python :: 3.6
